pysqlit/__init__.py
pysqlit/__version__.py
pysqlit/art.py
pysqlit/backup.py
pysqlit/btree.py
pysqlit/concurrent_storage.py
pysqlit/constants.py
pysqlit/core.py
pysqlit/cursor.py
pysqlit/database.py
pysqlit/ddl.py
pysqlit/enhanced_datafile.py
pysqlit/exceptions.py
pysqlit/integrity.py
pysqlit/models.py
pysqlit/parser.py
pysqlit/pysqlit_api.py
pysqlit/repl.py
pysqlit/storage.py
pysqlit/transaction.py
pysqlit-0.2.6.3.dist-info/WHEEL
pysqlit-0.2.6.3.dist-info/METADATA
pysqlit-0.2.6.3.dist-info/RECORD
