Metadata-Version: 2.3
Name: pysqlit
Version: 0.2.6.3
Summary: Python版sqlite引擎
Keywords: pysqlite,sqlite,sqlite3,pysqlit,PySqlit,PySqlite
Author: Python51888
License: MIT
Classifier: Development Status :: 5 - Production/Stable
Classifier: Programming Language :: Python :: 3.11
Classifier: License :: OSI Approved :: MIT License
Classifier: Operating System :: Microsoft :: Windows
Classifier: Intended Audience :: Developers
Classifier: Topic :: Software Development :: Libraries :: Python Modules
Classifier: Typing :: Typed
Requires-Dist: black>=22.0
Requires-Dist: mypy>=1.0
Requires-Dist: pytest>=7.0
Requires-Dist: pytest-cov>=4.0
Requires-Python: >=3.11
Project-URL: Documentation, https://zread.ai/Python51888/PySqlit
Project-URL: Homepage, https://github.com/Python51888/PySqlit
Project-URL: Repository, https://github.com/Python51888/PySqlit
